filedatasource/__init__.py
filedatasource/builder.py
filedatasource/csvfile.py
filedatasource/datafile.py
filedatasource/excel.py
filedatasource/utils.py
filedatasource-1.1.13.dist-info/LICENSE
filedatasource-1.1.13.dist-info/METADATA
filedatasource-1.1.13.dist-info/WHEEL
filedatasource-1.1.13.dist-info/top_level.txt
filedatasource-1.1.13.dist-info/RECORD
