Metadata-Version: 2.1
Name: filedatasource
Version: 1.1.13
Summary: Convert several file data sources (like typical CSV or Excel) to python objects in a easy manner.
Home-page: https://github.com/jmgomezsoriano/filedatasource
Author: José Manuel Gómez Soriano
Author-email: jmgomez.soriano@gmail.com
License: lGPLv3
Platform: UNKNOWN
Classifier: Programming Language :: Python :: 3
Classifier: License :: OSI Approved :: GNU General Public License v3 (GPLv3)
Classifier: Operating System :: OS Independent
Requires-Python: >=3.6
